mprov_ldap_manager/__init__.py
mprov_ldap_manager/admin.py
mprov_ldap_manager/apps.py
mprov_ldap_manager/middleware.py
mprov_ldap_manager/models.py
mprov_ldap_manager/serializers.py
mprov_ldap_manager/views.py
mprov_ldap_manager-0.0.4.dist-info/LICENSE
mprov_ldap_manager-0.0.4.dist-info/METADATA
mprov_ldap_manager-0.0.4.dist-info/WHEEL
mprov_ldap_manager-0.0.4.dist-info/top_level.txt
mprov_ldap_manager-0.0.4.dist-info/RECORD
