Metadata-Version: 2.1
Name: mprov-ldap-manager
Version: 0.0.4
Summary: An add-on to the mPCC to enable it to manage an LDAP directory.
Home-page: https://github.com/mprov-ng/mprov_ldap_manager
Author: Jason Williams
Author-email: jasonw@jhu.edu
Project-URL: Bug Tracker, https://github.com/mprov-ng/mprov_ldap_manager/issues
Classifier: Programming Language :: Python :: 3.8
Classifier: Programming Language :: Python :: 3.9
Classifier: Programming Language :: Python :: 3.10
Classifier: Programming Language :: Python :: 3.11
Classifier: Programming Language :: Python :: 3.12
Classifier: Operating System :: POSIX :: Linux
Classifier: License :: OSI Approved :: Apache Software License
Requires-Python: >=3.8
License-File: LICENSE
Requires-Dist: sh
Requires-Dist: mprov-django-ldapdb
Requires-Dist: django <3.3,>=3.2
